nonebot/adapters/bilibili/__init__.py
nonebot/adapters/bilibili/adapter.py
nonebot/adapters/bilibili/bili_interaction/__init__.py
nonebot/adapters/bilibili/bili_interaction/heartbeat.py
nonebot/adapters/bilibili/bili_interaction/interaction.py
nonebot/adapters/bilibili/bili_interaction/login_bili.py
nonebot/adapters/bilibili/bot.py
nonebot/adapters/bilibili/config.py
nonebot/adapters/bilibili/consts.py
nonebot/adapters/bilibili/event.py
nonebot/adapters/bilibili/message.py
nonebot/adapters/bilibili/types.py
nonebot/adapters/bilibili/utils.py
nonebot_adapter_bilibili-0.0.7.dist-info/WHEEL
nonebot_adapter_bilibili-0.0.7.dist-info/METADATA
nonebot_adapter_bilibili-0.0.7.dist-info/licenses/LICENSE
nonebot_adapter_bilibili-0.0.7.dist-info/RECORD
