Metadata-Version: 2.1
Name: nonebot-adapter-bilibili
Version: 0.0.7
Summary: 适配哔哩哔哩直播间ws协议的Nonebo2适配器
License: MIT
Author-email: wwweww <2646787260@qq.com>
Requires-Python: >=3.8
Requires-Dist: brotli>=1.1.0
Requires-Dist: nonebot2>=2.0.0rc2
Requires-Dist: qrcode-terminal>=0.8
Project-URL: repository, https://github.com/wwweww/adapter-bilibili
